canvas/__init__.py
canvas/apps.py
canvas/fileds.py
canvas/widgets.py
canvas/static/canvas/js/flashcanvas.min.js
canvas/static/canvas/js/jSignature.min.js
canvas/static/canvas/js/jq-signature.js
canvas/static/canvas/js/jquery.min.js
canvas/templates/canvas/sign_canvas.html
django_canvas_field-1.0.0.dist-info/LICENSE
django_canvas_field-1.0.0.dist-info/LICENSE-APACHE
django_canvas_field-1.0.0.dist-info/LICENSE-MIT
django_canvas_field-1.0.0.dist-info/METADATA
django_canvas_field-1.0.0.dist-info/WHEEL
django_canvas_field-1.0.0.dist-info/top_level.txt
django_canvas_field-1.0.0.dist-info/RECORD
