Metadata-Version: 2.1
Name: django-canvas-field
Version: 1.0.0
Summary: SignCanvasField
Author-email: "Mr.LLT" <384605850@qq.com>
Classifier: Programming Language :: Python :: 3
Classifier: License :: OSI Approved :: MIT License
Requires-Python: >=3.7
License-File: LICENSE
License-File: LICENSE-APACHE
License-File: LICENSE-MIT
Requires-Dist: django (>=3.2.4)
